{
  "slug": "preterite-vs-imperfect",
  "year": "cours",
  "title": {
    "en": "Preterite vs Imperfect",
    "nl": "Indefinido vs Imperfecto",
    "es": "Indefinido vs Imperfecto"
  },
  "grammarSections": [
    {
      "type": "explanation",
      "title": { "en": "When to Use Which?", "nl": "Wanneer Gebruik Je Wat?" },
      "content": {
        "en": "**Preterite (Indefinido)** — Completed actions:\n- Single events: Ayer **fui** al cine.\n- Start/end of actions: La fiesta **empezó** a las ocho.\n- Chain of events: **Llegué**, **comí** y **salí**.\n\n**Imperfect (Imperfecto)** — Ongoing/habitual:\n- Habitual actions: Siempre **iba** al parque.\n- Descriptions: El hombre **era** alto.\n- Background/context: **Hacía** frío y **llovía**.\n- Age/time: **Tenía** 15 años. **Eran** las once.\n\n**Together**: Imperfect sets the scene, preterite interrupts:\nMientras yo **dormía**, el teléfono **sonó**.\n\n📖 **501 Spanish Verbs** #2/#3 · **Practice Makes Perfect** p.111",
        "nl": "**Indefinido** — Voltooide handelingen:\n- Eenmalige gebeurtenissen: Ayer **fui** al cine.\n- Begin/einde: La fiesta **empezó** a las ocho.\n- Reeks gebeurtenissen: **Llegué**, **comí** y **salí**.\n\n**Imperfecto** — Voortdurend/gewoontehandelingen:\n- Gewoontes: Siempre **iba** al parque.\n- Beschrijvingen: El hombre **era** alto.\n- Achtergrond: **Hacía** frío y **llovía**.\n- Leeftijd/tijd: **Tenía** 15 años. **Eran** las once.\n\n**Samen**: Imperfecto schetst de scène, indefinido onderbreekt:\nMientras yo **dormía**, el teléfono **sonó**.\n\n📖 **501 Spanish Verbs** #2/#3 · **Practice Makes Perfect** p.111"
      }
    },
    {
      "type": "word_list",
      "title": { "en": "Preterite Triggers (Indefinido)", "nl": "Indefinido Signaalwoorden" },
      "items": [
        { "term": "Ayer", "translation": { "en": "Yesterday", "nl": "Gisteren" } },
        { "term": "Ayer por la mañana", "translation": { "en": "Yesterday morning", "nl": "Gisterochtend" } },
        { "term": "Ayer por la tarde", "translation": { "en": "Yesterday afternoon", "nl": "Gistermiddag" } },
        { "term": "Ayer por la noche", "translation": { "en": "Yesterday evening", "nl": "Gisteravond" } },
        { "term": "La semana pasada", "translation": { "en": "Last week", "nl": "Vorige week" } },
        { "term": "El año pasado", "translation": { "en": "Last year", "nl": "Vorig jaar" } },
        { "term": "El mes pasado", "translation": { "en": "Last month", "nl": "Vorige maand" } },
        { "term": "El fin de semana pasado", "translation": { "en": "Last weekend", "nl": "Vorig weekend" } },
        { "term": "El verano pasado", "translation": { "en": "Last summer", "nl": "Vorige zomer" } },
        { "term": "El lunes", "translation": { "en": "On Monday", "nl": "Op maandag" } },
        { "term": "Anoche", "translation": { "en": "Last night", "nl": "Gisteravond" } },
        { "term": "Anteayer", "translation": { "en": "The day before yesterday", "nl": "Eergisteren" } },
        { "term": "Hace 5 meses", "translation": { "en": "5 months ago", "nl": "5 maanden geleden" } },
        { "term": "Hace un rato", "translation": { "en": "A while ago", "nl": "Een tijdje geleden" } },
        { "term": "En 1966", "translation": { "en": "In 1966", "nl": "In 1966" } },
        { "term": "Por 5 minutos", "translation": { "en": "For 5 minutes", "nl": "Gedurende 5 minuten" } },
        { "term": "Esta mañana", "translation": { "en": "This morning", "nl": "Vanmorgen" } },
        { "term": "De repente", "translation": { "en": "Suddenly", "nl": "Plotseling" } },
        { "term": "En ese momento", "translation": { "en": "At that moment", "nl": "Op dat moment" } }
      ]
    },
    {
      "type": "word_list",
      "title": { "en": "Imperfect Triggers (Imperfecto)", "nl": "Imperfecto Signaalwoorden" },
      "items": [
        { "term": "Siempre", "translation": { "en": "Always", "nl": "Altijd" } },
        { "term": "A menudo", "translation": { "en": "Often", "nl": "Vaak" } },
        { "term": "De vez en cuando", "translation": { "en": "From time to time", "nl": "Af en toe" } },
        { "term": "Frecuentemente", "translation": { "en": "Frequently", "nl": "Frequent" } },
        { "term": "Con frecuencia", "translation": { "en": "Frequently", "nl": "Frequent" } },
        { "term": "A veces", "translation": { "en": "Sometimes", "nl": "Soms" } },
        { "term": "Cada día", "translation": { "en": "Every day", "nl": "Elke dag" } },
        { "term": "Cada semana", "translation": { "en": "Every week", "nl": "Elke week" } },
        { "term": "Cada año", "translation": { "en": "Every year", "nl": "Elk jaar" } },
        { "term": "Todos los días", "translation": { "en": "Every day", "nl": "Elke dag" } },
        { "term": "Todas las semanas", "translation": { "en": "Every week", "nl": "Elke week" } },
        { "term": "Todas las noches", "translation": { "en": "Every night", "nl": "Elke avond" } },
        { "term": "Generalmente", "translation": { "en": "Generally", "nl": "Over het algemeen" } },
        { "term": "Por lo general", "translation": { "en": "In general", "nl": "In het algemeen" } },
        { "term": "Normalmente", "translation": { "en": "Normally", "nl": "Normaal gesproken" } },
        { "term": "Típicamente", "translation": { "en": "Typically", "nl": "Typisch" } },
        { "term": "Usualmente", "translation": { "en": "Usually", "nl": "Gewoonlijk" } },
        { "term": "Cada verano", "translation": { "en": "Every summer", "nl": "Elke zomer" } },
        { "term": "Muchas veces", "translation": { "en": "Many times", "nl": "Vaak / Veel keer" } },
        { "term": "Tantas veces", "translation": { "en": "So many times", "nl": "Zo vaak" } },
        { "term": "Varias veces", "translation": { "en": "Several times", "nl": "Meerdere keren" } },
        { "term": "Nunca", "translation": { "en": "Never", "nl": "Nooit" } },
        { "term": "Mientras", "translation": { "en": "While", "nl": "Terwijl" } }
      ]
    }
  ],
  "exercises": [
    {
      "id": "pvi-triggers-01",
      "type": "multiple_choice",
      "instruction": { "en": "Which tense does this trigger word belong to?", "nl": "Bij welke tijd hoort dit signaalwoord?" },
      "items": [
        { "id": "trg-001", "sentence": "Ayer", "correctAnswers": ["Indefinido"], "hint": "Indefinido|Imperfecto" },
        { "id": "trg-002", "sentence": "Siempre", "correctAnswers": ["Imperfecto"], "hint": "Indefinido|Imperfecto" },
        { "id": "trg-003", "sentence": "La semana pasada", "correctAnswers": ["Indefinido"], "hint": "Indefinido|Imperfecto" },
        { "id": "trg-004", "sentence": "A menudo", "correctAnswers": ["Imperfecto"], "hint": "Indefinido|Imperfecto" },
        { "id": "trg-005", "sentence": "De repente", "correctAnswers": ["Indefinido"], "hint": "Indefinido|Imperfecto" },
        { "id": "trg-006", "sentence": "Cada día", "correctAnswers": ["Imperfecto"], "hint": "Indefinido|Imperfecto" },
        { "id": "trg-007", "sentence": "Anoche", "correctAnswers": ["Indefinido"], "hint": "Indefinido|Imperfecto" },
        { "id": "trg-008", "sentence": "Todos los días", "correctAnswers": ["Imperfecto"], "hint": "Indefinido|Imperfecto" },
        { "id": "trg-009", "sentence": "El año pasado", "correctAnswers": ["Indefinido"], "hint": "Indefinido|Imperfecto" },
        { "id": "trg-010", "sentence": "Normalmente", "correctAnswers": ["Imperfecto"], "hint": "Indefinido|Imperfecto" },
        { "id": "trg-011", "sentence": "En ese momento", "correctAnswers": ["Indefinido"], "hint": "Indefinido|Imperfecto" },
        { "id": "trg-012", "sentence": "Mientras", "correctAnswers": ["Imperfecto"], "hint": "Indefinido|Imperfecto" },
        { "id": "trg-013", "sentence": "Hace 5 meses", "correctAnswers": ["Indefinido"], "hint": "Indefinido|Imperfecto" },
        { "id": "trg-014", "sentence": "A veces", "correctAnswers": ["Imperfecto"], "hint": "Indefinido|Imperfecto" },
        { "id": "trg-015", "sentence": "Anteayer", "correctAnswers": ["Indefinido"], "hint": "Indefinido|Imperfecto" }
      ]
    },
    {
      "id": "pvi-story-01",
      "type": "fill_in_blank",
      "instruction": { "en": "Complete — Preterite or Imperfect? (Cuando era niña)", "nl": "Vul aan — Indefinido of Imperfecto? (Toen ik klein was)" },
      "items": [
        { "id": "pvi-001", "sentence": "Cuando yo ___ niña, tenía que tocar antes de abrir la puerta. (ser)", "correctAnswers": ["era"], "hint": "Background/description → imperfect" },
        { "id": "pvi-002", "sentence": "Yo ___ que tocar antes de abrir la puerta. (tener)", "correctAnswers": ["tenía"], "hint": "Habitual obligation → imperfect" },
        { "id": "pvi-003", "sentence": "Mis padres me ___ hablar cuando hablaban los mayores. (prohibir)", "correctAnswers": ["prohibían"], "hint": "Habitual rule → imperfect" },
        { "id": "pvi-004", "sentence": "Yo no ___ de la mesa hasta que todos terminaban de comer. (levantarse)", "correctAnswers": ["me levantaba"], "hint": "Habitual action → imperfect" },
        { "id": "pvi-005", "sentence": "Nosotros ___ a jugar al jardín. (salir)", "correctAnswers": ["salíamos"], "hint": "Habitual action → imperfect" },
        { "id": "pvi-006", "sentence": "No ___ permitido jugar antes de terminar los deberes. (estar)", "correctAnswers": ["estaba"], "hint": "Ongoing situation → imperfect" },
        { "id": "pvi-007", "sentence": "Después de la cena nosotros ___ los dientes. (lavarse)", "correctAnswers": ["nos lavábamos"], "hint": "Habitual action → imperfect" },
        { "id": "pvi-008", "sentence": "Los fines de semana ellos no ___ tan estrictos. (ser)", "correctAnswers": ["eran"], "hint": "Description → imperfect" },
        { "id": "pvi-009", "sentence": "Nosotros ___ jugar más tiempo en el jardín. (poder)", "correctAnswers": ["podíamos"], "hint": "Ongoing ability → imperfect" },
        { "id": "pvi-010", "sentence": "Pero un día nos ___ la tía Pepa. (visitar)", "correctAnswers": ["visitó"], "hint": "Single event → preterite" },
        { "id": "pvi-011", "sentence": "Mis padres le ___ que viniera a cuidarnos. (pedir)", "correctAnswers": ["pidieron"], "hint": "Single event → preterite" },
        { "id": "pvi-012", "sentence": "La tía Pepa nos ___ que nosotros podíamos hacer todo. (decir)", "correctAnswers": ["dijo"], "hint": "Single event → preterite" },
        { "id": "pvi-013", "sentence": "Nosotros ___ y jugamos en la casa. (correr)", "correctAnswers": ["corrimos"], "hint": "Chain of events → preterite" },
        { "id": "pvi-014", "sentence": "Aquel fin de semana ___ muy divertido. (ser)", "correctAnswers": ["fue"], "hint": "Completed assessment → preterite" }
      ]
    },
    {
      "id": "pvi-mallorca-01",
      "type": "fill_in_blank",
      "instruction": { "en": "Complete — Preterite or Imperfect? (Mi viaje a Mallorca)", "nl": "Vul aan — Indefinido of Imperfecto? (Mijn reis naar Mallorca)" },
      "items": [
        { "id": "pvi-015", "sentence": "El año pasado ___ en Mallorca con mi novio. (estar)", "correctAnswers": ["estuve"], "hint": "Completed event → preterite" },
        { "id": "pvi-016", "sentence": "___ a la isla para bañarnos en el mar. (ir)", "correctAnswers": ["Fuimos"], "hint": "Completed action → preterite" },
        { "id": "pvi-017", "sentence": "Lo ___ pasando muy bien cuando de repente Rudy se enfermó. (estar)", "correctAnswers": ["estábamos"], "hint": "Ongoing background → imperfect" },
        { "id": "pvi-018", "sentence": "Rudy ___ porque comió mucho. (enfermarse)", "correctAnswers": ["se enfermó"], "hint": "Sudden event → preterite" },
        { "id": "pvi-019", "sentence": "Él no ___ salir del hotel. (querer)", "correctAnswers": ["quería"], "hint": "Ongoing state → imperfect" },
        { "id": "pvi-020", "sentence": "Yo ___ aburrida sola en la playa. (estar)", "correctAnswers": ["estaba"], "hint": "Ongoing state → imperfect" },
        { "id": "pvi-021", "sentence": "Un chico alto me ___ amablemente. (saludar)", "correctAnswers": ["saludó"], "hint": "Single event → preterite" },
        { "id": "pvi-022", "sentence": "Me ___ a salir esa misma noche. (invitar)", "correctAnswers": ["invitó"], "hint": "Single event → preterite" },
        { "id": "pvi-023", "sentence": "No le ___ nada a Rudy. (decir)", "correctAnswers": ["dije"], "hint": "Single action → preterite" },
        { "id": "pvi-024", "sentence": "Me ___ a bailar con Carlos. (ir)", "correctAnswers": ["fui"], "hint": "Single event → preterite" },
        { "id": "pvi-025", "sentence": "Él ___ tan romántico que me enamoré de él. (ser)", "correctAnswers": ["era"], "hint": "Description → imperfect" },
        { "id": "pvi-026", "sentence": "Rudy ___ a casa. (regresar)", "correctAnswers": ["regresó"], "hint": "Completed event → preterite" }
      ]
    }
  ],
  "videoPlaceholder": {
    "title": { "en": "Teacher Explanation Video", "nl": "Uitleg Video Docent" },
    "description": { "en": "Video coming soon — Preterite vs Imperfect explained!", "nl": "Video komt binnenkort — Indefinido vs Imperfecto uitgelegd!" }
  }
}